{
  "standard": "Schematron 1.0 (ISO/IEC 19757-3)",
  "queryBinding": "xslt2",
  "output_format": ".sch",
  "namespaces": {
    "sch": "http://purl.oclc.org/dsdl/schematron",
    "xsi": "http://www.w3.org/2001/XMLSchema-instance",
    "rdf": "http://www.w3.org/1999/02/22-rdf-syntax-ns#",
    "xlink": "http://www.w3.org/1999/xlink",
    "dc": "http://www.purl.org/dc/elements/1.1/"
  },
  "file_header": "<?xml version='1.0' encoding='UTF-8'?>\n<sch:schema xmlns:sch=\"http://purl.oclc.org/dsdl/schematron\" queryBinding=\"xslt2\">\n  <sch:ns prefix=\"xsi\" uri=\"http://www.w3.org/2001/XMLSchema-instance\"/>\n  <sch:ns prefix=\"rdf\" uri=\"http://www.w3.org/1999/02/22-rdf-syntax-ns#\"/>\n  <sch:ns prefix=\"xlink\" uri=\"http://www.w3.org/1999/xlink\"/>\n  <sch:ns prefix=\"dc\" uri=\"http://www.purl.org/dc/elements/1.1/\"/>\n",
  "file_footer": "\n</sch:schema>",
  "structure": {
    "pattern": "sch:pattern id='brdp-a1-XXXXX' (lowercase)",
    "rule": "sch:rule context='[XPath expression]'",
    "assert": "sch:assert id='BRDP-A1-XXXXX' role='error' test='[condition]'"
  },
  "conversion_rules": {
    "prohibited_flag0": "XPath from objectPath goes in sch:rule @context. test is always false(). If the context matches, the rule always fails.",
    "mandatory_no_values_flag1": "Parent element goes in @context. test verifies the child exists.",
    "allowed_values": "Element or attribute goes in @context. test is an exists() OR chain: exists(node[(string(.) = 'val1') or (string(.) = 'val2')])",
    "no_flag_with_values": "Same as allowed_values but context is the element containing the values.",
    "assert_message": "Use the objectUse text from the BREX rule as the assert message content."
  },
  "few_shot_examples": [
    {
      "id": "BRDP-A1-00001",
      "pattern_id": "brdp-a1-00001",
      "rule_context": "//orig",
      "assert_test": "exists(@origname[(string(.) = 'ESCRIBANO MECHANICAL AND ENGINEERING SL') or (string(.) = 'INDRA SISTEMAS SA') or (string(.) = 'JEFATURA DEL MANDO DE APOYO LOGISTICO DEL ET') or (string(.) = 'SANTA BARBARA SISTEMAS SA') or (string(.) = 'TESS-DEFENCE SA') or (string(.) = 'SAPA OPERACIONES SL')])",
      "assert_message": "Códigos Origname permitidos."
    },
    {
      "id": "BRDP-A1-00002",
      "pattern_id": "brdp-a1-00002",
      "rule_context": "//orig[@origname='ESCRIBANO MECHANICAL AND ENGINEERING SL' and string(.) != '010CB']",
      "assert_test": "false()",
      "assert_message": "Si origname es ESCRIBANO MECHANICAL AND ENGINEERING SL, el valor debe ser 010CB."
    },
    {
      "id": "BRDP-A1-00003",
      "pattern_id": "brdp-a1-00003",
      "rule_context": "/dmodule[not(.//rpc)]",
      "assert_test": "false()",
      "assert_message": "rpc - ERROR: No se encontró la etiqueta rpc."
    },
    {
      "id": "BRDP-A1-00004",
      "pattern_id": "brdp-a1-00004",
      "rule_context": "/dmodule//rpc[not((string(.) = '010CB') or (string(.) = '0178B') or (string(.) = '3883B') or (string(.) = '0131B') or (string(.) = '9AEWB') or (string(.) = '0124B'))]",
      "assert_test": "false()",
      "assert_message": "Valores permitidos para rpc."
    },
    {
      "id": "BRDP-A1-00006",
      "pattern_id": "brdp-a1-00006",
      "rule_context": "/*[ not(//dmaddres/issno) and not(//identAndStatusSection/dmAddress/dmIdent/issueInfo/@issueNumber) ]",
      "assert_test": "false()",
      "assert_message": "Prohibir ausencia del dato de issue, debe existir dmaddres issno o atributo issueNumber en dmAddress dmIdent issueInfo."
    },
    {
      "id": "BRDP-A1-00007",
      "pattern_id": "brdp-a1-00007",
      "rule_context": "//dmaddres[not(language)]",
      "assert_test": "false()",
      "assert_message": "Prohibir dmaddres sin elemento language"
    },
    {
      "id": "BRDP-A1-00014",
      "pattern_id": "brdp-a1-00014",
      "rule_context": "/dmodule/idstatus[dmaddres/dmc/avee/incode='008']/dmaddres/dmtitle/infoname[not((string(.) = 'Registro de estándares técnicos'))]",
      "assert_test": "false()",
      "assert_message": "Valor permitido de infoname cuando incode='008'."
    },
    {
      "id": "BRDP-A1-00020",
      "pattern_id": "brdp-a1-00020",
      "rule_context": "/dmodule/idstatus[dmaddres/dmc/avee/incode='022']/dmaddres/dmtitle/infoname[not((string(.) = 'Business rules'))]",
      "assert_test": "false()",
      "assert_message": "Valor permitido de infoname cuando incode='022'."
    },
    {
      "id": "BRDP-A1-00029",
      "pattern_id": "brdp-a1-00029",
      "rule_context": "/dmodule/idstatus/dmaddres/dmtitle[not(normalize-space(techname))]",
      "assert_test": "false()",
      "assert_message": "DMC error. Falta techname ausente o vacío."
    },
    {
      "id": "BRDP-A1-00030",
      "pattern_id": "brdp-a1-00030",
      "rule_context": "/dmodule/idstatus[concat(dmaddres/dmc/avee/chapnum, dmaddres/dmc/avee/section, dmaddres/dmc/avee/subsect, dmaddres/dmc/avee/subject)='000000'] /dmaddres/dmtitle/techname[not((string(.) = 'SISTEMA GENERAL'))]",
      "assert_test": "false()",
      "assert_message": "Valor permitido de techname cuando SNS='000000'."
    },
    {
      "id": "BRDP-A1-00045",
      "pattern_id": "brdp-a1-00045",
      "rule_context": "//refdm[concat(avee/chapnum, avee/section, avee/subsect, avee/subject)='000000']/dmtitle/techname[not((string(.) = 'SISTEMA GENERAL'))]",
      "assert_test": "false()",
      "assert_message": "Valor permitido de techname cuando SNS='000000' en refdm."
    },
    {
      "id": "BRDP-A1-00046",
      "pattern_id": "brdp-a1-00046",
      "rule_context": "//idstatus/status/rfu[(//refdm/issno/@issno='001' or //refdm/issno/@issno='000' or //identAndStatusSection/dmAddress/dmIdent/issueInfo/@issueNumber='001' or //identAndStatusSection/dmAddress/dmIdent/issueInfo/@issueNumber='000') and not(normalize-space(.))]",
      "assert_test": "false()",
      "assert_message": "Prohibir cualquier rfu cuando el numero de issue sea 001 o 000."
    },
    {
      "id": "BRDP-A1-00047",
      "pattern_id": "brdp-a1-00047",
      "rule_context": "//*[@mark and ( string(//refdm/issno/@issno) = '001' or string(//identAndStatusSection/dmAddress/dmIdent/issueInfo/@issueNumber) = '001' )]",
      "assert_test": "false()",
      "assert_message": "Prohibir cualquier atributo mark en todo el documento cuando el numero de issue sea 001."
    },
    {
      "id": "BRDP-A1-00049",
      "pattern_id": "brdp-a1-00049",
      "rule_context": "//status/rfu[ string(//refdm/issno/@issno) = '000' or string(//identAndStatusSection/dmAddress/dmIdent/issueInfo/@issueNumber) = '000' ]",
      "assert_test": "false()",
      "assert_message": "Prohibir cualquier rfu cuando el numero de issue sea 000."
    },
    {
      "id": "BRDP-A1-00051",
      "pattern_id": "brdp-a1-00051",
      "rule_context": "(/dmodule/content/schedule/deftask | /dmodule/content/proced)/prelreqs/reqpers[not(perscat/@category)]",
      "assert_test": "false()",
      "assert_message": "En caso de existir las rutas schedule/deftask y proced, cada reqpers debe incluir perscat con atributo category."
    },
    {
      "id": "BRDP-A1-00052",
      "pattern_id": "brdp-a1-00052",
      "rule_context": "(/dmodule/content/schedule/deftask | /dmodule/content/proced)/prelreqs/reqpers[count(trade) != 1]",
      "assert_test": "false()",
      "assert_message": "En caso de existir las rutas schedule/deftask y proced, debe existir exactamente un trade por reqpers."
    },
    {
      "id": "BRDP-A1-00055",
      "pattern_id": "brdp-a1-00055",
      "rule_context": "(/dmodule/content/schedule/deftask | /dmodule/content/proced)/prelreqs/reqpers/esttime[contains(.,'.')]",
      "assert_test": "false()",
      "assert_message": "En caso de existir las rutas schedule/deftask y proced, esttime no debe usar punto; use coma como separador decimal."
    },
    {
      "id": "BRDP-A1-00059",
      "pattern_id": "brdp-a1-00059",
      "rule_context": "//supequi[not(qty)] | //supply[not(qty)] | //spare[not(qty)]",
      "assert_test": "false()",
      "assert_message": "Cada supequi/supply/spare debe tener su propio qty."
    },
    {
      "id": "BRDP-A1-00060",
      "pattern_id": "brdp-a1-00060",
      "rule_context": "//qty/@uom[not((string(.) = '*SI') or (string(.) = 'BF') or (string(.) = 'BQ') or (string(.) = 'CC') or (string(.) = 'CD') or (string(.) = 'CF') or (string(.) = 'CG') or (string(.) = 'CI') or (string(.) = 'CL') or (string(.) = 'CM') or (string(.) = 'CU') or (string(.) = 'CV') or (string(.) = 'CZ') or (string(.) = 'DC') or (string(.) = 'DE') or (string(.) = 'DG') or (string(.) = 'DL') or (string(.) = 'DM') or (string(.) = 'DW') or (string(.) = 'DZ') or (string(.) = 'EA') or (string(.) = 'EX') or (string(.) = 'FD') or (string(.) = 'FR') or (string(.) = 'FT') or (string(.) = 'FZ') or (string(.) = 'GB') or (string(.) = 'GC') or (string(.) = 'GG') or (string(.) = 'GI') or (string(.) = 'GL') or (string(.) = 'GM') or (string(.) = 'GN') or (string(.) = 'GR') or (string(.) = 'HD') or (string(.) = 'HF') or (string(.) = 'HG') or (string(.) = 'HL') or (string(.) = 'HM') or (string(.) = 'HP') or (string(.) = 'HS') or (string(.) = 'HW') or (string(.) = 'HY') or (string(.) = 'IN') or (string(.) = 'KG') or (string(.) = 'KM') or (string(.) = 'KR') or (string(.) = 'LB') or (string(.) = 'LF') or (string(.) = 'LI') or (string(.) = 'MC') or (string(.) = 'MF') or (string(.) = 'MG') or (string(.) = 'MI') or (string(.) = 'ML') or (string(.) = 'MM') or (string(.) = 'MN') or (string(.) = 'MR') or (string(.) = 'MX') or (string(.) = 'OZ') or (string(.) = 'PB') or (string(.) = 'PT') or (string(.) = 'QC') or (string(.) = 'QD') or (string(.) = 'QT') or (string(.) = 'RA') or (string(.) = 'RD') or (string(.) = 'RM') or (string(.) = 'RX') or (string(.) = 'SF') or (string(.) = 'SH') or (string(.) = 'SK') or (string(.) = 'SM') or (string(.) = 'SO') or (string(.) = 'SQ') or (string(.) = 'SY') or (string(.) = 'TM') or (string(.) = 'TN') or (string(.) = 'TO') or (string(.) = 'TT') or (string(.) = 'US') or (string(.) = 'YD'))]",
      "assert_test": "false()",
      "assert_message": "Decision by Company. Códigos uom permitidos."
    },
    {
      "id": "BRDP-A1-00061",
      "pattern_id": "brdp-a1-00061",
      "rule_context": "//supequi[ ( /dmodule/content/proced or /dmodule/content/schedule ) and not(nomen) ]",
      "assert_test": "false()",
      "assert_message": "Prohibir supequi sin elemento nomen"
    },
    {
      "id": "BRDP-A1-00064",
      "pattern_id": "brdp-a1-00064",
      "rule_context": "//supequi[ ( /dmodule/content/proced or /dmodule/content/schedule ) and not(nsn) ]",
      "assert_test": "false()",
      "assert_message": "Prohibir supequi sin elemento nsn"
    },
    {
      "id": "BRDP-A1-00066",
      "pattern_id": "brdp-a1-00066",
      "rule_context": "//pmd/opndurn[ not(@proced) and ( /dmodule/content/proced or /dmodule/content/schedule ) ]",
      "assert_test": "false()",
      "assert_message": "Prohibir opndurn sin atributo proced"
    },
    {
      "id": "BRDP-A1-00069",
      "pattern_id": "brdp-a1-00069",
      "rule_context": "//pmd/opndurn[@prelreqs and normalize-space(@prelreqs) != '0,00' and (//dmodule/content/proced or //dmodule/content/schedule) and ( translate(normalize-space(@prelreqs), '0123456789,', '') != '' or ((string-length(normalize-space(@prelreqs)) - string-length(translate(normalize-space(@prelreqs), ',', ''))) > 1) or ( contains(@prelreqs, ',') and ( string-length(substring-before(@prelreqs, ',')) = 0 or string-length(substring-before(@prelreqs, ',')) > 8 or string-length(substring-after(@prelreqs, ',')) < 1 or string-length(substring-after(@prelreqs, ',')) > 2 )) or ( not(contains(@prelreqs, ',')) and string-length(normalize-space(@prelreqs)) > 8 ))]",
      "assert_test": "false()",
      "assert_message": "Prohibir prelreqs con formato invalido cuando no es cero"
    },
    {
      "id": "BRDP-A1-00072",
      "pattern_id": "brdp-a1-00072",
      "rule_context": "/dmodule[not(//actref)]",
      "assert_test": "false()",
      "assert_message": "//actref - ERROR: No se encontró ninguna etiqueta actref. Es obligatoria."
    },
    {
      "id": "BRDP-A1-00074",
      "pattern_id": "brdp-a1-00074",
      "rule_context": "/dmodule/content//table//applic",
      "assert_test": "false()",
      "assert_message": "Table - ERROR: applic no permitido dentro de table."
    },
    {
      "id": "BRDP-A1-00075",
      "pattern_id": "brdp-a1-00075",
      "rule_context": "//inlineapplics[not(applic[@id])]",
      "assert_test": "false()",
      "assert_message": "Prohibir inlineapplics sin al menos un applic con identificador"
    },
    {
      "id": "BRDP-A1-00080",
      "pattern_id": "brdp-a1-00080",
      "rule_context": "/dmodule//xref[not(@xidtype)]",
      "assert_test": "false()",
      "assert_message": "xref - ERROR: Nodo xref sin atributo xidtype."
    },
    {
      "id": "BRDP-A1-00081",
      "pattern_id": "brdp-a1-00081",
      "rule_context": "//reqconds/reqcblst//cblst[@cbaction and ( /dmodule/content/proced or /dmodule/content/schedule )]",
      "assert_test": "false()",
      "assert_message": "Prohibir cblst con atributo cbaction dentro de reqcblst"
    },
    {
      "id": "BRDP-A1-00085",
      "pattern_id": "brdp-a1-00085",
      "rule_context": "/dmodule/content//table[not(@frame='topbot')]",
      "assert_test": "false()",
      "assert_message": "Table - ERROR: El atributo frame debe ser topbot."
    },
    {
      "id": "BRDP-A1-00086",
      "pattern_id": "brdp-a1-00086",
      "rule_context": "/dmodule/content//table[not(@id) or not(starts-with(@id,'tab-')) or string-length(@id) != 8 or string-length(substring(@id,5)) != 4 or translate(substring(@id,5),'0123456789','') != '']",
      "assert_test": "false()",
      "assert_message": "Table - ERROR: El atributo id debe tener formato tab-YYYY."
    },
    {
      "id": "BRDP-A1-00087",
      "pattern_id": "brdp-a1-00087",
      "rule_context": "/dmodule/content//table[@authdoc]",
      "assert_test": "false()",
      "assert_message": "Table - ERROR: Atributo prohibido authdoc presente."
    },
    {
      "id": "BRDP-A1-00091",
      "pattern_id": "brdp-a1-00091",
      "rule_context": "//figure[.//graphic//hotspot and not(.//legend)]",
      "assert_test": "false()",
      "assert_message": "Prohibir figure con hotspots sin legend"
    },
    {
      "id": "BRDP-A1-00092",
      "pattern_id": "brdp-a1-00092",
      "rule_context": "//figure[.//graphic//hotspot and count(.//legend/deflist/term) != count(.//graphic//hotspot) ]",
      "assert_test": "false()",
      "assert_message": "Prohibir desajuste entre numero de term y numero de hotspots en la misma figure"
    },
    {
      "id": "BRDP-A1-00097",
      "pattern_id": "brdp-a1-00097",
      "rule_context": "//techstd",
      "assert_test": "exists(tpbase[(string(.) = 'S1000D')])",
      "assert_message": "Prohibir techstd con tpbase distinto de S1000D."
    },
    {
      "id": "BRDP-A1-00098",
      "pattern_id": "brdp-a1-00098",
      "rule_context": "//status/qa/firstver",
      "assert_test": "exists(@type[(string(.) = 'tabtop')])",
      "assert_message": "Obligatorio el atributo type de firstver y su valor debe ser tabtop"
    },
    {
      "id": "BRDP-A1-00099",
      "pattern_id": "brdp-a1-00099",
      "rule_context": "//avehcfg/jacked[@status][not((string(.) = 'yes') or (string(.) = 'no') or (string(.) = 'na'))]",
      "assert_test": "false()",
      "assert_message": "(SOPTE BREX 3.9.5.2.1.9-2.2)El valor del atributo status de jacked no esta permitido."
    },
    {
      "id": "BRDP-A1-00100",
      "pattern_id": "brdp-a1-00100",
      "rule_context": "//dmodule",
      "assert_test": "exists(@xsi:noNamespaceSchemaLocation[(string(.) = 'http://www.s1000d.org/S1000D_3-0-1/xml_schema_flat/appliccrossreftable.xsd') or (string(.) = 'http://www.s1000d.org/S1000D_3-0-1/xml_schema_flat/brex.xsd') or (string(.) = 'http://www.s1000d.org/S1000D_3-0-1/xml_schema_flat/comment.xsd') or (string(.) = 'http://www.s1000d.org/S1000D_3-0-1/xml_schema_flat/condcrossreftable.xsd') or (string(.) = 'http://www.s1000d.org/S1000D_3-0-1/xml_schema_flat/container.xsd') or (string(.) = 'http://www.s1000d.org/S1000D_3-0-1/xml_schema_flat/ddn.xsd') or (string(.) = 'http://www.s1000d.org/S1000D_3-0-1/xml_schema_flat/descript.xsd') or (string(.) = 'http://www.s1000d.org/S1000D_3-0-1/xml_schema_flat/dml.xsd') or (string(.) = 'http://www.s1000d.org/S1000D_3-0-1/xml_schema_flat/fault.xsd') or (string(.) = 'http://www.s1000d.org/S1000D_3-0-1/xml_schema_flat/ipd.xsd') or (string(.) = 'http://www.s1000d.org/S1000D_3-0-1/xml_schema_flat/pm.xsd') or (string(.) = 'http://www.s1000d.org/S1000D_3-0-1/xml_schema_flat/prdcrossreftable.xsd') or (string(.) = 'http://www.s1000d.org/S1000D_3-0-1/xml_schema_flat/proced.xsd') or (string(.) = 'http://www.s1000d.org/S1000D_3-0-1/xml_schema_flat/schedul.xsd') or (string(.) = 'http://www.s1000d.org/S1000D_3-0-1/xml_schema_flat/techrep.xsd') or (string(.) = 'http://www.s1000d.org/S1000D_3-0-1/xml_schema_flat/wrngdata.xsd') or (string(.) = 'http://www.s1000d.org/S1000D_3-0-1/xml_schema_flat/wrngflds.xsd') or (string(.) = 'http://www.s1000d.org/S1000D_3-0-1/xml_schema_master/dm/appliccrossreftableSchema.xsd') or (string(.) = 'http://www.s1000d.org/S1000D_3-0-1/xml_schema_master/dm/brexSchema.xsd') or (string(.) = 'http://www.s1000d.org/S1000D_3-0-1/xml_schema_master/comment/commentSchema.xsd') or (string(.) = 'http://www.s1000d.org/S1000D_3-0-1/xml_schema_master/dm/condcrossreftableSchema.xsd') or (string(.) = 'http://www.s1000d.org/S1000D_3-0-1/xml_schema/dm/containerSchema.xsd') or (string(.) = 'http://www.s1000d.org/S1000D_3-0-1/xml_schema_master/ddn/ddnSchema.xsd') or (string(.) = 'http://www.s1000d.org/S1000D_3-0-1/xml_schema_master/dm/descriptSchema.xsd') or (string(.) = 'http://www.s1000d.org/S1000D_3-0-1/xml_schema_master/dml/dmlSchema.xsd') or (string(.) = 'http://www.s1000d.org/S1000D_3-0-1/xml_schema_master/dm/faultSchema.xsd') or (string(.) = 'http://www.s1000d.org/S1000D_3-0-1/xml_schema_master/dm/ipdSchema.xsd') or (string(.) = 'http://www.s1000d.org/S1000D_3-0-1/xml_schema_master/pm/pmSchema.xsd') or (string(.) = 'http://www.s1000d.org/S1000D_3-0-1/xml_schema_master/dm/prdcrossreftableSchema.xsd') or (string(.) = 'http://www.s1000d.org/S1000D_3-0-1/xml_schema_master/dm/procedSchema.xsd') or (string(.) = 'http://www.s1000d.org/S1000D_3-0-1/xml_schema_master/dm/schedulSchema.xsd') or (string(.) = 'http://www.s1000d.org/S1000D_3-0-1/xml_schema_master/dm/techrepSchema.xsd') or (string(.) = 'http://www.s1000d.org/S1000D_3-0-1/xml_schema_master/dm/wrngdataSchema.xsd') or (string(.) = 'http://www.s1000d.org/S1000D_3-0-1/xml_schema_master/dm/wrngfldsSchema.xsd')])",
      "assert_message": "Obligatorio que la ubicacion de esquema pertenezca a la lista XMLDM aprobada"
    }
  ]
}
